init_agent_docker/__init__.py
init_agent_docker/__main__.py
init_agent_docker/agent.py
init_agent_docker-0.1.2.dist-info/METADATA
init_agent_docker-0.1.2.dist-info/WHEEL
init_agent_docker-0.1.2.dist-info/top_level.txt
init_agent_docker-0.1.2.dist-info/RECORD
