Metadata-Version: 2.4
Name: init-agent-docker
Version: 0.1.2
Summary: init-agent-docker.
Author-email: LauLe <levanlau.net@gmail.com>
License: MIT
Requires-Python: >=3.8
